.gitignore
MANIFEST.in
README.rst
mdx.sublime-project
mdx.sublime-workspace
mdxbuilder.sublime-workspace
setup.py
mdx/__init__.py
mdx/config.py
mdx/decorators.py
mdx/loaders.py
mdx/writers.py
mdx.egg-info/PKG-INFO
mdx.egg-info/SOURCES.txt
mdx.egg-info/dependency_links.txt
mdx.egg-info/not-zip-safe
mdx.egg-info/requires.txt
mdx.egg-info/top_level.txt
mdx/syntax/__init__.py
mdx/tests/__init__.py
mdx/tests/test_mdx.py