Metadata-Version: 1.0
Name: mdx
Version: 0.1
Summary: A simple package for generating mdx scripts
Home-page: http://github.com/tiagotaveiragomes/mdx
Author: Tiago Taveira-Gomes
Author-email: tiago.taveira@me.com
License: MIT
Keywords: MDX builder bi business intelligence
Platform: UNKNOWN
